{"province": "hubei", "province_name": "湖北", "year": 2024, "track": "physics", "track_cn": "物理类", "source": "省考试院 / eol.cn (一分一段表全表)", "source_url": "https://gaokao.eol.cn/hu_bei/dongtai/202406/t20240625_2619340.shtml", "note": "湖北 2024 3+1+2 物理类 全表 (eol.cn 转 湖北省教育考试院)", "count": 546, "rows": [{"score": 695, "count": 44, "cumulative": 44}, {"score": 694, "count": 6, "cumulative": 50}, {"score": 693, "count": 10, "cumulative": 60}, {"score": 692, "count": 11, "cumulative": 71}, {"score": 691, "count": 12, "cumulative": 83}, {"score": 690, "count": 15, "cumulative": 98}, {"score": 689, "count": 17, "cumulative": 115}, {"score": 688, "count": 13, "cumulative": 128}, {"score": 687, "count": 9, "cumulative": 137}, {"score": 686, "count": 22, "cumulative": 159}, {"score": 685, "count": 14, "cumulative": 173}, {"score": 684, "count": 14, "cumulative": 187}, {"score": 683, "count": 21, "cumulative": 208}, {"score": 682, "count": 31, "cumulative": 239}, {"score": 681, "count": 32, "cumulative": 271}, {"score": 680, "count": 29, "cumulative": 300}, {"score": 679, "count": 32, "cumulative": 332}, {"score": 678, "count": 40, "cumulative": 372}, {"score": 677, "count": 40, "cumulative": 412}, {"score": 676, "count": 34, "cumulative": 446}, {"score": 675, "count": 42, "cumulative": 488}, {"score": 674, "count": 38, "cumulative": 526}, {"score": 673, "count": 55, "cumulative": 581}, {"score": 672, "count": 37, "cumulative": 618}, {"score": 671, "count": 53, "cumulative": 671}, {"score": 670, "count": 55, "cumulative": 726}, {"score": 669, "count": 62, "cumulative": 788}, {"score": 668, "count": 54, "cumulative": 842}, {"score": 667, "count": 56, "cumulative": 898}, {"score": 666, "count": 65, "cumulative": 963}, {"score": 665, "count": 83, "cumulative": 1046}, {"score": 664, "count": 90, "cumulative": 1136}, {"score": 663, "count": 105, "cumulative": 1241}, {"score": 662, "count": 73, "cumulative": 1314}, {"score": 661, "count": 102, "cumulative": 1416}, {"score": 660, "count": 91, "cumulative": 1507}, {"score": 659, "count": 96, "cumulative": 1603}, {"score": 658, "count": 116, "cumulative": 1719}, {"score": 657, "count": 128, "cumulative": 1847}, {"score": 656, "count": 124, "cumulative": 1971}, {"score": 655, "count": 109, "cumulative": 2080}, {"score": 654, "count": 113, "cumulative": 2193}, {"score": 653, "count": 122, "cumulative": 2315}, {"score": 652, "count": 138, "cumulative": 2453}, {"score": 651, "count": 143, "cumulative": 2596}, {"score": 650, "count": 131, "cumulative": 2727}, {"score": 649, "count": 152, "cumulative": 2879}, {"score": 648, "count": 154, "cumulative": 3033}, {"score": 647, "count": 185, "cumulative": 3218}, {"score": 646, "count": 144, "cumulative": 3362}, {"score": 645, "count": 170, "cumulative": 3532}, {"score": 644, "count": 180, "cumulative": 3712}, {"score": 643, "count": 189, "cumulative": 3901}, {"score": 642, "count": 184, "cumulative": 4085}, {"score": 641, "count": 202, "cumulative": 4287}, {"score": 640, "count": 208, "cumulative": 4495}, {"score": 639, "count": 215, "cumulative": 4710}, {"score": 638, "count": 180, "cumulative": 4890}, {"score": 637, "count": 209, "cumulative": 5099}, {"score": 636, "count": 227, "cumulative": 5326}, {"score": 635, "count": 217, "cumulative": 5543}, {"score": 634, "count": 213, "cumulative": 5756}, {"score": 633, "count": 226, "cumulative": 5982}, {"score": 632, "count": 261, "cumulative": 6243}, {"score": 631, "count": 266, "cumulative": 6509}, {"score": 630, "count": 268, "cumulative": 6777}, {"score": 629, "count": 279, "cumulative": 7056}, {"score": 628, "count": 300, "cumulative": 7356}, {"score": 627, "count": 303, "cumulative": 7659}, {"score": 626, "count": 251, "cumulative": 7910}, {"score": 625, "count": 305, "cumulative": 8215}, {"score": 624, "count": 271, "cumulative": 8486}, {"score": 623, "count": 274, "cumulative": 8760}, {"score": 622, "count": 307, "cumulative": 9067}, {"score": 621, "count": 290, "cumulative": 9357}, {"score": 620, "count": 344, "cumulative": 9701}, {"score": 619, "count": 334, "cumulative": 10035}, {"score": 618, "count": 337, "cumulative": 10372}, {"score": 617, "count": 308, "cumulative": 10680}, {"score": 616, "count": 378, "cumulative": 11058}, {"score": 615, "count": 337, "cumulative": 11395}, {"score": 614, "count": 361, "cumulative": 11756}, {"score": 613, "count": 402, "cumulative": 12158}, {"score": 612, "count": 378, "cumulative": 12536}, {"score": 611, "count": 396, "cumulative": 12932}, {"score": 610, "count": 383, "cumulative": 13315}, {"score": 609, "count": 413, "cumulative": 13728}, {"score": 608, "count": 388, "cumulative": 14116}, {"score": 607, "count": 403, "cumulative": 14519}, {"score": 606, "count": 415, "cumulative": 14934}, {"score": 605, "count": 422, "cumulative": 15356}, {"score": 604, "count": 412, "cumulative": 15768}, {"score": 603, "count": 462, "cumulative": 16230}, {"score": 602, "count": 455, "cumulative": 16685}, {"score": 601, "count": 454, "cumulative": 17139}, {"score": 600, "count": 474, "cumulative": 17613}, {"score": 599, "count": 471, "cumulative": 18084}, {"score": 598, "count": 479, "cumulative": 18563}, {"score": 597, "count": 500, "cumulative": 19063}, {"score": 596, "count": 474, "cumulative": 19537}, {"score": 595, "count": 468, "cumulative": 20005}, {"score": 594, "count": 488, "cumulative": 20493}, {"score": 593, "count": 493, "cumulative": 20986}, {"score": 592, "count": 525, "cumulative": 21511}, {"score": 591, "count": 486, "cumulative": 21997}, {"score": 590, "count": 476, "cumulative": 22473}, {"score": 589, "count": 598, "cumulative": 23071}, {"score": 588, "count": 525, "cumulative": 23596}, {"score": 587, "count": 536, "cumulative": 24132}, {"score": 586, "count": 549, "cumulative": 24681}, {"score": 585, "count": 543, "cumulative": 25224}, {"score": 584, "count": 568, "cumulative": 25792}, {"score": 583, "count": 600, "cumulative": 26392}, {"score": 582, "count": 599, "cumulative": 26991}, {"score": 581, "count": 600, "cumulative": 27591}, {"score": 580, "count": 641, "cumulative": 28232}, {"score": 579, "count": 669, "cumulative": 28901}, {"score": 578, "count": 561, "cumulative": 29462}, {"score": 577, "count": 618, "cumulative": 30080}, {"score": 576, "count": 633, "cumulative": 30713}, {"score": 575, "count": 638, "cumulative": 31351}, {"score": 574, "count": 618, "cumulative": 31969}, {"score": 573, "count": 644, "cumulative": 32613}, {"score": 572, "count": 656, "cumulative": 33269}, {"score": 571, "count": 688, "cumulative": 33957}, {"score": 570, "count": 664, "cumulative": 34621}, {"score": 569, "count": 685, "cumulative": 35306}, {"score": 568, "count": 672, "cumulative": 35978}, {"score": 567, "count": 681, "cumulative": 36659}, {"score": 566, "count": 660, "cumulative": 37319}, {"score": 565, "count": 688, "cumulative": 38007}, {"score": 564, "count": 672, "cumulative": 38679}, {"score": 563, "count": 669, "cumulative": 39348}, {"score": 562, "count": 694, "cumulative": 40042}, {"score": 561, "count": 671, "cumulative": 40713}, {"score": 560, "count": 725, "cumulative": 41438}, {"score": 559, "count": 698, "cumulative": 42136}, {"score": 558, "count": 719, "cumulative": 42855}, {"score": 557, "count": 762, "cumulative": 43617}, {"score": 556, "count": 709, "cumulative": 44326}, {"score": 555, "count": 725, "cumulative": 45051}, {"score": 554, "count": 790, "cumulative": 45841}, {"score": 553, "count": 697, "cumulative": 46538}, {"score": 552, "count": 744, "cumulative": 47282}, {"score": 551, "count": 737, "cumulative": 48019}, {"score": 550, "count": 789, "cumulative": 48808}, {"score": 549, "count": 730, "cumulative": 49538}, {"score": 548, "count": 757, "cumulative": 50295}, {"score": 547, "count": 749, "cumulative": 51044}, {"score": 546, "count": 790, "cumulative": 51834}, {"score": 545, "count": 694, "cumulative": 52528}, {"score": 544, "count": 730, "cumulative": 53258}, {"score": 543, "count": 797, "cumulative": 54055}, {"score": 542, "count": 782, "cumulative": 54837}, {"score": 541, "count": 839, "cumulative": 55676}, {"score": 540, "count": 823, "cumulative": 56499}, {"score": 539, "count": 757, "cumulative": 57256}, {"score": 538, "count": 795, "cumulative": 58051}, {"score": 537, "count": 821, "cumulative": 58872}, {"score": 536, "count": 844, "cumulative": 59716}, {"score": 535, "count": 772, "cumulative": 60488}, {"score": 534, "count": 804, "cumulative": 61292}, {"score": 533, "count": 801, "cumulative": 62093}, {"score": 532, "count": 811, "cumulative": 62904}, {"score": 531, "count": 791, "cumulative": 63695}, {"score": 530, "count": 781, "cumulative": 64476}, {"score": 529, "count": 884, "cumulative": 65360}, {"score": 528, "count": 838, "cumulative": 66198}, {"score": 527, "count": 843, "cumulative": 67041}, {"score": 526, "count": 821, "cumulative": 67862}, {"score": 525, "count": 816, "cumulative": 68678}, {"score": 524, "count": 825, "cumulative": 69503}, {"score": 523, "count": 759, "cumulative": 70262}, {"score": 522, "count": 846, "cumulative": 71108}, {"score": 521, "count": 834, "cumulative": 71942}, {"score": 520, "count": 844, "cumulative": 72786}, {"score": 519, "count": 822, "cumulative": 73608}, {"score": 518, "count": 825, "cumulative": 74433}, {"score": 517, "count": 843, "cumulative": 75276}, {"score": 516, "count": 769, "cumulative": 76045}, {"score": 515, "count": 829, "cumulative": 76874}, {"score": 514, "count": 828, "cumulative": 77702}, {"score": 513, "count": 855, "cumulative": 78557}, {"score": 512, "count": 843, "cumulative": 79400}, {"score": 511, "count": 809, "cumulative": 80209}, {"score": 510, "count": 837, "cumulative": 81046}, {"score": 509, "count": 842, "cumulative": 81888}, {"score": 508, "count": 864, "cumulative": 82752}, {"score": 507, "count": 876, "cumulative": 83628}, {"score": 506, "count": 837, "cumulative": 84465}, {"score": 505, "count": 865, "cumulative": 85330}, {"score": 504, "count": 851, "cumulative": 86181}, {"score": 503, "count": 809, "cumulative": 86990}, {"score": 502, "count": 851, "cumulative": 87841}, {"score": 501, "count": 826, "cumulative": 88667}, {"score": 500, "count": 834, "cumulative": 89501}, {"score": 499, "count": 811, "cumulative": 90312}, {"score": 498, "count": 800, "cumulative": 91112}, {"score": 497, "count": 853, "cumulative": 91965}, {"score": 496, "count": 785, "cumulative": 92750}, {"score": 495, "count": 867, "cumulative": 93617}, {"score": 494, "count": 821, "cumulative": 94438}, {"score": 493, "count": 807, "cumulative": 95245}, {"score": 492, "count": 790, "cumulative": 96035}, {"score": 491, "count": 826, "cumulative": 96861}, {"score": 490, "count": 859, "cumulative": 97720}, {"score": 489, "count": 823, "cumulative": 98543}, {"score": 488, "count": 877, "cumulative": 99420}, {"score": 487, "count": 770, "cumulative": 100190}, {"score": 486, "count": 851, "cumulative": 101041}, {"score": 485, "count": 853, "cumulative": 101894}, {"score": 484, "count": 828, "cumulative": 102722}, {"score": 483, "count": 888, "cumulative": 103610}, {"score": 482, "count": 819, "cumulative": 104429}, {"score": 481, "count": 856, "cumulative": 105285}, {"score": 480, "count": 812, "cumulative": 106097}, {"score": 479, "count": 856, "cumulative": 106953}, {"score": 478, "count": 814, "cumulative": 107767}, {"score": 477, "count": 803, "cumulative": 108570}, {"score": 476, "count": 814, "cumulative": 109384}, {"score": 475, "count": 845, "cumulative": 110229}, {"score": 474, "count": 852, "cumulative": 111081}, {"score": 473, "count": 796, "cumulative": 111877}, {"score": 472, "count": 783, "cumulative": 112660}, {"score": 471, "count": 833, "cumulative": 113493}, {"score": 470, "count": 833, "cumulative": 114326}, {"score": 469, "count": 748, "cumulative": 115074}, {"score": 468, "count": 826, "cumulative": 115900}, {"score": 467, "count": 809, "cumulative": 116709}, {"score": 466, "count": 850, "cumulative": 117559}, {"score": 465, "count": 817, "cumulative": 118376}, {"score": 464, "count": 797, "cumulative": 119173}, {"score": 463, "count": 782, "cumulative": 119955}, {"score": 462, "count": 744, "cumulative": 120699}, {"score": 461, "count": 865, "cumulative": 121564}, {"score": 460, "count": 791, "cumulative": 122355}, {"score": 459, "count": 817, "cumulative": 123172}, {"score": 458, "count": 795, "cumulative": 123967}, {"score": 457, "count": 753, "cumulative": 124720}, {"score": 456, "count": 764, "cumulative": 125484}, {"score": 455, "count": 804, "cumulative": 126288}, {"score": 454, "count": 780, "cumulative": 127068}, {"score": 453, "count": 826, "cumulative": 127894}, {"score": 452, "count": 745, "cumulative": 128639}, {"score": 451, "count": 785, "cumulative": 129424}, {"score": 450, "count": 790, "cumulative": 130214}, {"score": 449, "count": 790, "cumulative": 131004}, {"score": 448, "count": 782, "cumulative": 131786}, {"score": 447, "count": 776, "cumulative": 132562}, {"score": 446, "count": 773, "cumulative": 133335}, {"score": 445, "count": 782, "cumulative": 134117}, {"score": 444, "count": 773, "cumulative": 134890}, {"score": 443, "count": 752, "cumulative": 135642}, {"score": 442, "count": 794, "cumulative": 136436}, {"score": 441, "count": 797, "cumulative": 137233}, {"score": 440, "count": 750, "cumulative": 137983}, {"score": 439, "count": 753, "cumulative": 138736}, {"score": 438, "count": 771, "cumulative": 139507}, {"score": 437, "count": 733, "cumulative": 140240}, {"score": 436, "count": 760, "cumulative": 141000}, {"score": 435, "count": 767, "cumulative": 141767}, {"score": 434, "count": 749, "cumulative": 142516}, {"score": 433, "count": 731, "cumulative": 143247}, {"score": 432, "count": 734, "cumulative": 143981}, {"score": 431, "count": 724, "cumulative": 144705}, {"score": 430, "count": 742, "cumulative": 145447}, {"score": 429, "count": 732, "cumulative": 146179}, {"score": 428, "count": 767, "cumulative": 146946}, {"score": 427, "count": 748, "cumulative": 147694}, {"score": 426, "count": 735, "cumulative": 148429}, {"score": 425, "count": 744, "cumulative": 149173}, {"score": 424, "count": 705, "cumulative": 149878}, {"score": 423, "count": 703, "cumulative": 150581}, {"score": 422, "count": 719, "cumulative": 151300}, {"score": 421, "count": 740, "cumulative": 152040}, {"score": 420, "count": 663, "cumulative": 152703}, {"score": 419, "count": 687, "cumulative": 153390}, {"score": 418, "count": 725, "cumulative": 154115}, {"score": 417, "count": 668, "cumulative": 154783}, {"score": 416, "count": 676, "cumulative": 155459}, {"score": 415, "count": 719, "cumulative": 156178}, {"score": 414, "count": 663, "cumulative": 156841}, {"score": 413, "count": 637, "cumulative": 157478}, {"score": 412, "count": 724, "cumulative": 158202}, {"score": 411, "count": 683, "cumulative": 158885}, {"score": 410, "count": 652, "cumulative": 159537}, {"score": 409, "count": 684, "cumulative": 160221}, {"score": 408, "count": 671, "cumulative": 160892}, {"score": 407, "count": 653, "cumulative": 161545}, {"score": 406, "count": 677, "cumulative": 162222}, {"score": 405, "count": 729, "cumulative": 162951}, {"score": 404, "count": 681, "cumulative": 163632}, {"score": 403, "count": 675, "cumulative": 164307}, {"score": 402, "count": 637, "cumulative": 164944}, {"score": 401, "count": 652, "cumulative": 165596}, {"score": 400, "count": 682, "cumulative": 166278}, {"score": 399, "count": 692, "cumulative": 166970}, {"score": 398, "count": 671, "cumulative": 167641}, {"score": 397, "count": 656, "cumulative": 168297}, {"score": 396, "count": 652, "cumulative": 168949}, {"score": 395, "count": 647, "cumulative": 169596}, {"score": 394, "count": 611, "cumulative": 170207}, {"score": 393, "count": 634, "cumulative": 170841}, {"score": 392, "count": 628, "cumulative": 171469}, {"score": 391, "count": 640, "cumulative": 172109}, {"score": 390, "count": 641, "cumulative": 172750}, {"score": 389, "count": 670, "cumulative": 173420}, {"score": 388, "count": 667, "cumulative": 174087}, {"score": 387, "count": 581, "cumulative": 174668}, {"score": 386, "count": 624, "cumulative": 175292}, {"score": 385, "count": 632, "cumulative": 175924}, {"score": 384, "count": 615, "cumulative": 176539}, {"score": 383, "count": 641, "cumulative": 177180}, {"score": 382, "count": 597, "cumulative": 177777}, {"score": 381, "count": 634, "cumulative": 178411}, {"score": 380, "count": 634, "cumulative": 179045}, {"score": 379, "count": 645, "cumulative": 179690}, {"score": 378, "count": 642, "cumulative": 180332}, {"score": 377, "count": 633, "cumulative": 180965}, {"score": 376, "count": 630, "cumulative": 181595}, {"score": 375, "count": 580, "cumulative": 182175}, {"score": 374, "count": 593, "cumulative": 182768}, {"score": 373, "count": 622, "cumulative": 183390}, {"score": 372, "count": 605, "cumulative": 183995}, {"score": 371, "count": 563, "cumulative": 184558}, {"score": 370, "count": 587, "cumulative": 185145}, {"score": 369, "count": 600, "cumulative": 185745}, {"score": 368, "count": 632, "cumulative": 186377}, {"score": 367, "count": 582, "cumulative": 186959}, {"score": 366, "count": 580, "cumulative": 187539}, {"score": 365, "count": 563, "cumulative": 188102}, {"score": 364, "count": 548, "cumulative": 188650}, {"score": 363, "count": 567, "cumulative": 189217}, {"score": 362, "count": 595, "cumulative": 189812}, {"score": 361, "count": 553, "cumulative": 190365}, {"score": 360, "count": 546, "cumulative": 190911}, {"score": 359, "count": 596, "cumulative": 191507}, {"score": 358, "count": 608, "cumulative": 192115}, {"score": 357, "count": 541, "cumulative": 192656}, {"score": 356, "count": 543, "cumulative": 193199}, {"score": 355, "count": 596, "cumulative": 193795}, {"score": 354, "count": 532, "cumulative": 194327}, {"score": 353, "count": 559, "cumulative": 194886}, {"score": 352, "count": 562, "cumulative": 195448}, {"score": 351, "count": 566, "cumulative": 196014}, {"score": 350, "count": 579, "cumulative": 196593}, {"score": 349, "count": 551, "cumulative": 197144}, {"score": 348, "count": 569, "cumulative": 197713}, {"score": 347, "count": 567, "cumulative": 198280}, {"score": 346, "count": 574, "cumulative": 198854}, {"score": 345, "count": 602, "cumulative": 199456}, {"score": 344, "count": 507, "cumulative": 199963}, {"score": 343, "count": 535, "cumulative": 200498}, {"score": 342, "count": 567, "cumulative": 201065}, {"score": 341, "count": 582, "cumulative": 201647}, {"score": 340, "count": 536, "cumulative": 202183}, {"score": 339, "count": 541, "cumulative": 202724}, {"score": 338, "count": 556, "cumulative": 203280}, {"score": 337, "count": 473, "cumulative": 203753}, {"score": 336, "count": 533, "cumulative": 204286}, {"score": 335, "count": 520, "cumulative": 204806}, {"score": 334, "count": 517, "cumulative": 205323}, {"score": 333, "count": 529, "cumulative": 205852}, {"score": 332, "count": 538, "cumulative": 206390}, {"score": 331, "count": 534, "cumulative": 206924}, {"score": 330, "count": 502, "cumulative": 207426}, {"score": 329, "count": 482, "cumulative": 207908}, {"score": 328, "count": 464, "cumulative": 208372}, {"score": 327, "count": 517, "cumulative": 208889}, {"score": 326, "count": 510, "cumulative": 209399}, {"score": 325, "count": 519, "cumulative": 209918}, {"score": 324, "count": 500, "cumulative": 210418}, {"score": 323, "count": 510, "cumulative": 210928}, {"score": 322, "count": 485, "cumulative": 211413}, {"score": 321, "count": 486, "cumulative": 211899}, {"score": 320, "count": 473, "cumulative": 212372}, {"score": 319, "count": 515, "cumulative": 212887}, {"score": 318, "count": 493, "cumulative": 213380}, {"score": 317, "count": 491, "cumulative": 213871}, {"score": 316, "count": 477, "cumulative": 214348}, {"score": 315, "count": 478, "cumulative": 214826}, {"score": 314, "count": 468, "cumulative": 215294}, {"score": 313, "count": 487, "cumulative": 215781}, {"score": 312, "count": 465, "cumulative": 216246}, {"score": 311, "count": 452, "cumulative": 216698}, {"score": 310, "count": 477, "cumulative": 217175}, {"score": 309, "count": 474, "cumulative": 217649}, {"score": 308, "count": 442, "cumulative": 218091}, {"score": 307, "count": 457, "cumulative": 218548}, {"score": 306, "count": 451, "cumulative": 218999}, {"score": 305, "count": 467, "cumulative": 219466}, {"score": 304, "count": 482, "cumulative": 219948}, {"score": 303, "count": 458, "cumulative": 220406}, {"score": 302, "count": 442, "cumulative": 220848}, {"score": 301, "count": 414, "cumulative": 221262}, {"score": 300, "count": 442, "cumulative": 221704}, {"score": 299, "count": 432, "cumulative": 222136}, {"score": 298, "count": 375, "cumulative": 222511}, {"score": 297, "count": 454, "cumulative": 222965}, {"score": 296, "count": 422, "cumulative": 223387}, {"score": 295, "count": 403, "cumulative": 223790}, {"score": 294, "count": 396, "cumulative": 224186}, {"score": 293, "count": 411, "cumulative": 224597}, {"score": 292, "count": 421, "cumulative": 225018}, {"score": 291, "count": 392, "cumulative": 225410}, {"score": 290, "count": 396, "cumulative": 225806}, {"score": 289, "count": 407, "cumulative": 226213}, {"score": 288, "count": 347, "cumulative": 226560}, {"score": 287, "count": 406, "cumulative": 226966}, {"score": 286, "count": 367, "cumulative": 227333}, {"score": 285, "count": 400, "cumulative": 227733}, {"score": 284, "count": 409, "cumulative": 228142}, {"score": 283, "count": 413, "cumulative": 228555}, {"score": 282, "count": 355, "cumulative": 228910}, {"score": 281, "count": 360, "cumulative": 229270}, {"score": 280, "count": 362, "cumulative": 229632}, {"score": 279, "count": 344, "cumulative": 229976}, {"score": 278, "count": 316, "cumulative": 230292}, {"score": 277, "count": 358, "cumulative": 230650}, {"score": 276, "count": 330, "cumulative": 230980}, {"score": 275, "count": 337, "cumulative": 231317}, {"score": 274, "count": 356, "cumulative": 231673}, {"score": 273, "count": 345, "cumulative": 232018}, {"score": 272, "count": 325, "cumulative": 232343}, {"score": 271, "count": 329, "cumulative": 232672}, {"score": 270, "count": 338, "cumulative": 233010}, {"score": 269, "count": 325, "cumulative": 233335}, {"score": 268, "count": 334, "cumulative": 233669}, {"score": 267, "count": 331, "cumulative": 234000}, {"score": 266, "count": 307, "cumulative": 234307}, {"score": 265, "count": 295, "cumulative": 234602}, {"score": 264, "count": 277, "cumulative": 234879}, {"score": 263, "count": 294, "cumulative": 235173}, {"score": 262, "count": 277, "cumulative": 235450}, {"score": 261, "count": 303, "cumulative": 235753}, {"score": 260, "count": 241, "cumulative": 235994}, {"score": 259, "count": 285, "cumulative": 236279}, {"score": 258, "count": 259, "cumulative": 236538}, {"score": 257, "count": 266, "cumulative": 236804}, {"score": 256, "count": 239, "cumulative": 237043}, {"score": 255, "count": 267, "cumulative": 237310}, {"score": 254, "count": 232, "cumulative": 237542}, {"score": 253, "count": 243, "cumulative": 237785}, {"score": 252, "count": 238, "cumulative": 238023}, {"score": 251, "count": 235, "cumulative": 238258}, {"score": 250, "count": 205, "cumulative": 238463}, {"score": 249, "count": 225, "cumulative": 238688}, {"score": 248, "count": 220, "cumulative": 238908}, {"score": 247, "count": 229, "cumulative": 239137}, {"score": 246, "count": 192, "cumulative": 239329}, {"score": 245, "count": 191, "cumulative": 239520}, {"score": 244, "count": 201, "cumulative": 239721}, {"score": 243, "count": 197, "cumulative": 239918}, {"score": 242, "count": 191, "cumulative": 240109}, {"score": 241, "count": 189, "cumulative": 240298}, {"score": 240, "count": 156, "cumulative": 240454}, {"score": 239, "count": 173, "cumulative": 240627}, {"score": 238, "count": 158, "cumulative": 240785}, {"score": 237, "count": 161, "cumulative": 240946}, {"score": 236, "count": 154, "cumulative": 241100}, {"score": 235, "count": 161, "cumulative": 241261}, {"score": 234, "count": 149, "cumulative": 241410}, {"score": 233, "count": 144, "cumulative": 241554}, {"score": 232, "count": 142, "cumulative": 241696}, {"score": 231, "count": 145, "cumulative": 241841}, {"score": 230, "count": 150, "cumulative": 241991}, {"score": 229, "count": 133, "cumulative": 242124}, {"score": 228, "count": 112, "cumulative": 242236}, {"score": 227, "count": 104, "cumulative": 242340}, {"score": 226, "count": 131, "cumulative": 242471}, {"score": 225, "count": 101, "cumulative": 242572}, {"score": 224, "count": 98, "cumulative": 242670}, {"score": 223, "count": 95, "cumulative": 242765}, {"score": 222, "count": 108, "cumulative": 242873}, {"score": 221, "count": 83, "cumulative": 242956}, {"score": 220, "count": 106, "cumulative": 243062}, {"score": 219, "count": 86, "cumulative": 243148}, {"score": 218, "count": 95, "cumulative": 243243}, {"score": 217, "count": 90, "cumulative": 243333}, {"score": 216, "count": 69, "cumulative": 243402}, {"score": 215, "count": 75, "cumulative": 243477}, {"score": 214, "count": 69, "cumulative": 243546}, {"score": 213, "count": 75, "cumulative": 243621}, {"score": 212, "count": 59, "cumulative": 243680}, {"score": 211, "count": 61, "cumulative": 243741}, {"score": 210, "count": 66, "cumulative": 243807}, {"score": 209, "count": 53, "cumulative": 243860}, {"score": 208, "count": 61, "cumulative": 243921}, {"score": 207, "count": 55, "cumulative": 243976}, {"score": 206, "count": 57, "cumulative": 244033}, {"score": 205, "count": 51, "cumulative": 244084}, {"score": 204, "count": 41, "cumulative": 244125}, {"score": 203, "count": 49, "cumulative": 244174}, {"score": 202, "count": 44, "cumulative": 244218}, {"score": 201, "count": 41, "cumulative": 244259}, {"score": 200, "count": 36, "cumulative": 244295}, {"score": 199, "count": 36, "cumulative": 244331}, {"score": 198, "count": 38, "cumulative": 244369}, {"score": 197, "count": 43, "cumulative": 244412}, {"score": 196, "count": 30, "cumulative": 244442}, {"score": 195, "count": 31, "cumulative": 244473}, {"score": 194, "count": 31, "cumulative": 244504}, {"score": 193, "count": 28, "cumulative": 244532}, {"score": 192, "count": 42, "cumulative": 244574}, {"score": 191, "count": 25, "cumulative": 244599}, {"score": 190, "count": 24, "cumulative": 244623}, {"score": 189, "count": 20, "cumulative": 244643}, {"score": 188, "count": 25, "cumulative": 244668}, {"score": 187, "count": 29, "cumulative": 244697}, {"score": 186, "count": 24, "cumulative": 244721}, {"score": 185, "count": 21, "cumulative": 244742}, {"score": 184, "count": 17, "cumulative": 244759}, {"score": 183, "count": 15, "cumulative": 244774}, {"score": 182, "count": 19, "cumulative": 244793}, {"score": 181, "count": 14, "cumulative": 244807}, {"score": 180, "count": 21, "cumulative": 244828}, {"score": 179, "count": 14, "cumulative": 244842}, {"score": 178, "count": 9, "cumulative": 244851}, {"score": 177, "count": 12, "cumulative": 244863}, {"score": 176, "count": 11, "cumulative": 244874}, {"score": 175, "count": 9, "cumulative": 244883}, {"score": 174, "count": 11, "cumulative": 244894}, {"score": 173, "count": 6, "cumulative": 244900}, {"score": 172, "count": 5, "cumulative": 244905}, {"score": 171, "count": 10, "cumulative": 244915}, {"score": 170, "count": 9, "cumulative": 244924}, {"score": 169, "count": 5, "cumulative": 244929}, {"score": 168, "count": 3, "cumulative": 244932}, {"score": 167, "count": 8, "cumulative": 244940}, {"score": 166, "count": 6, "cumulative": 244946}, {"score": 165, "count": 10, "cumulative": 244956}, {"score": 164, "count": 6, "cumulative": 244962}, {"score": 163, "count": 2, "cumulative": 244964}, {"score": 162, "count": 10, "cumulative": 244974}, {"score": 161, "count": 8, "cumulative": 244982}, {"score": 160, "count": 6, "cumulative": 244988}, {"score": 159, "count": 7, "cumulative": 244995}, {"score": 158, "count": 6, "cumulative": 245001}, {"score": 157, "count": 3, "cumulative": 245004}, {"score": 156, "count": 5, "cumulative": 245009}, {"score": 155, "count": 3, "cumulative": 245012}, {"score": 154, "count": 2, "cumulative": 245014}, {"score": 153, "count": 6, "cumulative": 245020}, {"score": 152, "count": 6, "cumulative": 245026}, {"score": 151, "count": 3, "cumulative": 245029}, {"score": 150, "count": 9, "cumulative": 245038}]}