{
  "_kind": "高水平运动队招生院校 list (2024)",
  "_year": 2024,
  "_source": [
    "https://gaokao.eol.cn/ystc/tytcs/",
    "https://www.gaokzx.com/c/202311/84627.html",
    "各校招生网"
  ],
  "schools": [
    {"school":"清华大学","zs_code":"10003","sports":["田径","篮球","射击","游泳","排球"]},
    {"school":"北京大学","zs_code":"10001","sports":["田径","男子篮球","女子篮球","乒乓球","羽毛球","游泳","男子足球"]},
    {"school":"复旦大学","zs_code":"10246","sports":["男子排球","女子排球","女子足球","武术套路","田径","游泳"]},
    {"school":"上海交通大学","zs_code":"10248","sports":["乒乓球","网球","羽毛球","足球"]},
    {"school":"浙江大学","zs_code":"10335","sports":["篮球","排球","游泳","射击","田径"]},
    {"school":"南京大学","zs_code":"10284","sports":["田径","篮球","网球"]},
    {"school":"华东师范大学","zs_code":"10269","sports":["田径","男子篮球"]},
    {"school":"山东大学","zs_code":"10422","sports":["排球","田径","篮球"]},
    {"school":"河海大学","zs_code":"10294","sports":["乒乓球"]},
    {"school":"暨南大学","zs_code":"10559","sports":["武术套路"]},
    {"school":"重庆大学","zs_code":"10611","sports":["篮球","足球","排球","田径"]},
    {"school":"北京航空航天大学","zs_code":"10006","sports":["田径","篮球"]},
    {"school":"武汉大学","zs_code":"10486","sports":["田径","篮球","足球","排球"]},
    {"school":"中山大学","zs_code":"10558","sports":["排球","篮球","田径"]},
    {"school":"四川大学","zs_code":"10610","sports":["田径","篮球","排球"]},
    {"school":"西安交通大学","zs_code":"10698","sports":["篮球","足球","网球"]},
    {"school":"厦门大学","zs_code":"10384","sports":["田径","篮球","排球"]},
    {"school":"中国科学技术大学","zs_code":"10358","sports":["田径"]},
    {"school":"华中科技大学","zs_code":"10487","sports":["篮球","足球"]},
    {"school":"天津大学","zs_code":"10056","sports":["篮球","足球","排球"]},
    {"school":"苏州大学","zs_code":"10285","sports":["田径","乒乓球"]},
    {"school":"北京理工大学","zs_code":"10007","sports":["篮球","足球"]}
  ]
}
